{
	"songs": [
		[ "Stained, Brutal Calamity", "", [ 255, 255, 255 ] ],
		[ "Roar of the Jungle Dragon", "", [ 255, 255, 255 ] ],
		[ "Interstellar Stomper", "", [ 255, 255, 255 ] ],
		[ "The Step Below Hell", "", [ 255, 255, 255 ] ],
		[ "sanctuary", "", [ 255, 255, 255 ] ],
		[ "Unholy Insurgency", "", [ 255, 255, 255 ] ],
		[ "The Leviathan Trilogy", "", [ 255, 255, 255 ] ],
		[ "Guardian of The Former Seas", "", [ 255, 255, 255 ] ],
		[ "Feral Amalgamation", "", [ 255, 255, 255 ] ],
		[ "The Heaven-Sent Abomination", "", [ 255, 255, 255 ] ]
		

	],
	"hiddenUntilUnlocked": true,
	"hideFreeplay": false,
	"weekBackground": "",
	"difficulties": "Death",
	"weekCharacters": [ "", "", "" ],
	"storyName": "Calamity OST",
	"weekName": "pack2",
	"freeplayColor": [ 255, 0, 0 ],
	"hideStoryMode": true,
	"weekBefore": "pack1",
	"startUnlocked": true
}